setup.py
cyffld2/__init__.py
cyffld2/_ffld2.cpp
cyffld2/_ffld2.pxd
cyffld2/_ffld2.pyx
cyffld2/detection.py
cyffld2/paths.py
cyffld2/training.py
cyffld2.egg-info/PKG-INFO
cyffld2.egg-info/SOURCES.txt
cyffld2.egg-info/dependency_links.txt
cyffld2.egg-info/requires.txt
cyffld2.egg-info/top_level.txt
cyffld2/ffld2/HOGPyramid.cpp
cyffld2/ffld2/HOGPyramid.h
cyffld2/ffld2/Intersector.h
cyffld2/ffld2/JPEGImage.cpp
cyffld2/ffld2/JPEGImage.h
cyffld2/ffld2/LBFGS.cpp
cyffld2/ffld2/LBFGS.h
cyffld2/ffld2/Mixture.cpp
cyffld2/ffld2/Mixture.h
cyffld2/ffld2/Model.cpp
cyffld2/ffld2/Model.h
cyffld2/ffld2/Object.cpp
cyffld2/ffld2/Object.h
cyffld2/ffld2/Patchwork.cpp
cyffld2/ffld2/Patchwork.h
cyffld2/ffld2/Rectangle.cpp
cyffld2/ffld2/Rectangle.h
cyffld2/ffld2/Scene.cpp
cyffld2/ffld2/Scene.h
cyffld2/ffld2/SimpleOpt.h
cyffld2/ffld2/test.cpp
cyffld2/ffld2/train.cpp
cyffld2/ffld2/lib/ffld2.cpp
cyffld2/ffld2/lib/ffld2.h
cyffld2/ffld2/models/headhunter_dpm_baseline.txt